{"type": "Feature", "id": 12523208, "geometry": {"type": "Point", "coordinates": [-159.800003, -21.200001]}, "properties": {"woe:id": 12523208, "woe:parent_id": 1064303, "woe:name": "Rarotonga International Airport", "woe:placetype": 14, "woe:placetype_name": "Airport", "woe:lang": "ENG", "iso:country": "CK", "meta:provider": ["geoplanet:7.3.1", "geoplanet:7.3.2", "geoplanet:7.4.0", "geoplanet:7.4.1", "geoplanet:7.5.1", "geoplanet:7.5.2", "geoplanet:7.6.0", "geoplanet:7.8.1", "geoplanet:7.9.0", "geoplanet:7.10.0", "geoplanet:8.0.0", "woeplanet:8.0.0"], "meta:indexed": "2020-08-20T20:13:21.149446", "woe:alias_ENG_V": ["Rarotonga Airport", "Rarotonga International", "RAR", "RAR Airport"], "meta:updated": "2020-10-14T11:23:48.626410", "woe:hierarchy": {"continent": 24865674, "country": 23424795, "town": 0, "planet": 1, "county": 0, "suburb": 0, "state": 24549675, "region": 0, "localadmin": 0}, "woe:timezone_id": 28350964, "woe:hash": "2knr7stjn13k", "woe:centroid": [-159.800003, -21.200001], "geom:latitude": -21.200001, "geom:longitude": -159.800003, "geom:hash": "2knr7stjn13k", "woe:latitude": -21.200001, "geom:centroid": [-159.800003, -21.200001], "woe:longitude": -159.800003, "woe:repo": "woeplanet-airport-ck", "geom:area": 0.0, "woe:scale": 19}}